mcp_fuzzer/__init__.py
mcp_fuzzer/__main__.py
mcp_fuzzer/corpus.py
mcp_fuzzer/env.py
mcp_fuzzer/events.py
mcp_fuzzer/exceptions.py
mcp_fuzzer/protocol_types.py
mcp_fuzzer/spec_version.py
mcp_fuzzer/types.py
mcp_fuzzer/auth/__init__.py
mcp_fuzzer/auth/loaders.py
mcp_fuzzer/auth/manager.py
mcp_fuzzer/auth/providers.py
mcp_fuzzer/cli/__init__.py
mcp_fuzzer/cli/config_merge.py
mcp_fuzzer/cli/entrypoint.py
mcp_fuzzer/cli/parser.py
mcp_fuzzer/cli/startup_info.py
mcp_fuzzer/cli/validators.py
mcp_fuzzer/client/__init__.py
mcp_fuzzer/client/base.py
mcp_fuzzer/client/constants.py
mcp_fuzzer/client/main.py
mcp_fuzzer/client/protocol_client.py
mcp_fuzzer/client/settings.py
mcp_fuzzer/client/tool_client.py
mcp_fuzzer/client/adapters/__init__.py
mcp_fuzzer/client/adapters/config_adapter.py
mcp_fuzzer/client/ports/__init__.py
mcp_fuzzer/client/ports/config_port.py
mcp_fuzzer/client/runtime/__init__.py
mcp_fuzzer/client/runtime/argv_builder.py
mcp_fuzzer/client/runtime/async_runner.py
mcp_fuzzer/client/runtime/pipeline.py
mcp_fuzzer/client/runtime/retry.py
mcp_fuzzer/client/runtime/run_plan.py
mcp_fuzzer/client/safety/__init__.py
mcp_fuzzer/client/safety/controller.py
mcp_fuzzer/client/transport/__init__.py
mcp_fuzzer/client/transport/auth_port.py
mcp_fuzzer/client/transport/factory.py
mcp_fuzzer/config/__init__.py
mcp_fuzzer/config/core/__init__.py
mcp_fuzzer/config/core/constants.py
mcp_fuzzer/config/core/manager.py
mcp_fuzzer/config/extensions/__init__.py
mcp_fuzzer/config/extensions/transports.py
mcp_fuzzer/config/loading/__init__.py
mcp_fuzzer/config/loading/discovery.py
mcp_fuzzer/config/loading/loader.py
mcp_fuzzer/config/loading/parser.py
mcp_fuzzer/config/loading/search_params.py
mcp_fuzzer/config/schema/__init__.py
mcp_fuzzer/config/schema/builders.py
mcp_fuzzer/config/schema/composer.py
mcp_fuzzer/fuzz_engine/__init__.py
mcp_fuzzer/fuzz_engine/executor/__init__.py
mcp_fuzzer/fuzz_engine/executor/async_executor.py
mcp_fuzzer/fuzz_engine/executor/batch_executor.py
mcp_fuzzer-0.2.9.dist-info/licenses/LICENSE
mcp_fuzzer-0.2.9.dist-info/METADATA
mcp_fuzzer-0.2.9.dist-info/WHEEL
mcp_fuzzer-0.2.9.dist-info/entry_points.txt
mcp_fuzzer-0.2.9.dist-info/top_level.txt
mcp_fuzzer-0.2.9.dist-info/RECORD
