Metadata-Version: 2.4
Name: mcp-fuzzer
Version: 0.2.9
Summary: MCP server fuzzer client and utilities
Author-email: Prince Roshan <princekrroshan01@gmail.com>
License: MIT License
Project-URL: Homepage, https://github.com/agent-hellboy/mcp-server-fuzzer
Project-URL: Repository, https://github.com/agent-hellboy/mcp-server-fuzzer
Project-URL: Issues, https://github.com/agent-hellboy/mcp-server-fuzzer/issues
Project-URL: Documentation, https://agent-hellboy.github.io/mcp-server-fuzzer
Keywords: mcp,fuzzing,testing,json-rpc
Classifier: Development Status :: 3 - Alpha
Classifier: Intended Audience :: Developers
Classifier: License :: OSI Approved :: MIT License
Classifier: Programming Language :: Python :: 3
Classifier: Programming Language :: Python :: 3.10
Classifier: Programming Language :: Python :: 3.11
Classifier: Programming Language :: Python :: 3.12
Classifier: Programming Language :: Python :: 3.13
Classifier: Programming Language :: Python :: 3.14
Requires-Python: >=3.10
License-File: LICENSE
Requires-Dist: httpx
Requires-Dist: hypothesis
Requires-Dist: jsonschema>=4.25.1
Requires-Dist: rich
Requires-Dist: pyyaml>=6.0
Requires-Dist: psutil>=5.9.0
Requires-Dist: emoji
Provides-Extra: dev
Requires-Dist: pytest>=7.0.0; extra == "dev"
Requires-Dist: pytest-cov>=4.0.0; extra == "dev"
Requires-Dist: pytest-asyncio>=0.21.0; extra == "dev"
Requires-Dist: ruff>=0.1.0; extra == "dev"
Requires-Dist: black>=23.0.0; extra == "dev"
Requires-Dist: mypy>=1.0.0; extra == "dev"
Requires-Dist: pre-commit>=3.5.0; extra == "dev"
Requires-Dist: tox>=4.0.0; extra == "dev"
Provides-Extra: docs
Requires-Dist: mkdocs>=1.5.0; extra == "docs"
Requires-Dist: mkdocs-material>=9.0.0; extra == "docs"
Requires-Dist: mkdocs-minify-plugin>=0.7.0; extra == "docs"
Provides-Extra: test
Requires-Dist: pytest>=7.0.0; extra == "test"
Requires-Dist: pytest-cov>=4.0.0; extra == "test"
Requires-Dist: pytest-asyncio>=0.21.0; extra == "test"
Dynamic: license-file
